examples/PyKinectBodyGame.py
examples/PyKinectInfraRed.py
examples/__init__.py
pykinect2024/PyKinect2024.py
pykinect2024/PyKinectRuntime.py
pykinect2024/__init__.py
pykinect2024-0.1.2024.dist-info/LICENSE.txt
pykinect2024-0.1.2024.dist-info/METADATA
pykinect2024-0.1.2024.dist-info/WHEEL
pykinect2024-0.1.2024.dist-info/top_level.txt
pykinect2024-0.1.2024.dist-info/RECORD
